setup.cfg
setup.py
namespaces/__init__.py
namespaces/frozennamespace.py
namespaces/namespace.py
namespaces/utils.py
namespaces.egg-info/PKG-INFO
namespaces.egg-info/SOURCES.txt
namespaces.egg-info/dependency_links.txt
namespaces.egg-info/pbr.json
namespaces.egg-info/requires.txt
namespaces.egg-info/top_level.txt