Metadata-Version: 1.0
Name: namespaces
Version: 4.2.0
Summary: Python dictionaries with items also accessible via dot-notation
Home-page: https://github.com/pcattori/namespaces
Author: Pedro Cattori
Author-email: pcattori@gmail.com
License: MIT
Platform: UNKNOWN
